shabti_util/__init__.py
shabti_util/auth.py
shabti_util-0.3a2.dist-info/METADATA
shabti_util-0.3a2.dist-info/WHEEL
shabti_util-0.3a2.dist-info/RECORD
