Metadata-Version: 2.4
Name: shabti-util
Version: 0.3a2
Requires-Python: >=3.10
Requires-Dist: pyyaml
